firebase/.version
firebase/__classpath__.py
firebase/__init__.py
firebase/__main__.py
firebase/welcome.txt
firebase/core/__init__.py
firebase/core/agent_config.py
firebase/core/file_processor.py
firebase/core/firebase.py
firebase/core/firebase_auth.py
firebase/domain/__init__.py
firebase/domain/firebase_dto.py
firebase/exception/__init__.py
firebase/exception/exceptions.py
firebase/resources/application.properties
firebase/resources/sample.txt
firebase/resources/sample2.txt
hspylib_firebase-0.9.155.dist-info/METADATA
hspylib_firebase-0.9.155.dist-info/WHEEL
hspylib_firebase-0.9.155.dist-info/top_level.txt
hspylib_firebase-0.9.155.dist-info/RECORD
