Metadata-Version: 2.2
Name: hspylib-firebase
Version: 0.9.155
Summary: HsPyLib - Firebase integration
Home-page: https://github.com/yorevs/hspylib
Author: Hugo Saporetti Junior
Author-email: yorevs@hotmail.com
License: MIT
Project-URL: GitHub, https://github.com/yorevs/hspylib
Project-URL: PyPi, https://pypi.org/project/hspylib-firebase/
Keywords: firebase,google,integration,application
Platform: Darwin
Platform: Linux
Classifier: License :: OSI Approved :: MIT License
Classifier: Programming Language :: Python :: 3.10
Classifier: Operating System :: MacOS :: MacOS X
Classifier: Operating System :: POSIX :: Linux
Classifier: Operating System :: Unix
Classifier: Development Status :: 3 - Alpha
Classifier: Environment :: Console
Classifier: Natural Language :: English
Classifier: Topic :: Terminals
Classifier: Intended Audience :: Developers
Requires-Python: >=3.10
Requires-Dist: hspylib
Requires-Dist: hspylib-datasource
Requires-Dist: hspylib-clitt
Requires-Dist: requests>=2.32.3
Requires-Dist: urllib3>=1.26.20
Requires-Dist: firebase-admin>=6.5.0
Dynamic: author
Dynamic: author-email
Dynamic: classifier
Dynamic: description
Dynamic: description-content-type
Dynamic: home-page
Dynamic: keywords
Dynamic: license
Dynamic: platform
Dynamic: project-url
Dynamic: requires-dist
Dynamic: requires-python
Dynamic: summary
